LICENSE
MANIFEST.in
README.rst
setup.py
corrections/__init__.py
corrections.egg-info/PKG-INFO
corrections.egg-info/SOURCES.txt
corrections.egg-info/dependency_links.txt
corrections.egg-info/not-zip-safe
corrections.egg-info/requires.txt
corrections.egg-info/top_level.txt