Metadata-Version: 1.1
Name: corrections
Version: 0.2.3
Summary: UNKNOWN
Home-page: https://github.com/plausibility/corrections
Author: plausibility
Author-email: chris@gibsonsec.org
License: MIT
Keywords: twitter bot corrections
Platform: UNKNOWN
Classifier: Development Status :: 3 - Alpha
Classifier: Intended Audience :: Developers
Classifier: License :: OSI Approved :: MIT License
Classifier: Operating System :: OS Independent
Classifier: Programming Language :: Python :: 2
